{
   "sourceName": "Toonitalia",
   "iconUrl": "https://github.com/Dicast3/SoraSauce/blob/main/Toonitalia/icon.jpg",
   "author": {
       "name": "DxC",
       "icon": "xxx"
   },
   "version": "0.0.1",
   "language": "Italian",
   "streamType": "HLS",
   "quality": "720p",
   "baseUrl": "https://toonitalia.xyz/wp-json/",
   "searchBaseUrl": "https://toonitalia.xyz/wp-json/wp/v2/posts?search=%s",
   "scriptUrl": "https://github.com/Dicast3/SoraSauce/blob/main/Toonitalia/Toonitalia.js",
   "asyncJS": true
}
